{
  "run_name": "run_20251016_182106_50HEMIUSDT_ITERATIVE_$1_OPTUNA",
  "timestamp": "2025-10-16T18:21:06.031196",
  "ranges": {
    "selected_files_optimization": [
      "50HEMIUSDT-klines-1s-2025-09-01_to_2025-09-30.parquet"
    ],
    "vol_period_max_optimization": 30,
    "vol_period_min_optimization": 5,
    "aggressive_mode_optimization": false,
    "bracket_timeout_candles_max_optimization": 50,
    "min_growth_pct_min_optimization": 0.5,
    "select_profile_optimization": "0Orders",
    "bracket_timeout_candles_min_optimization": 1,
    "bracket_offset_pct_max_optimization": 1.0,
    "take_profit_pct_min_optimization": 1.5,
    "load_profile_optimization": false,
    "natr_min_max_optimization": 1.0,
    "range_period_max_optimization": 30,
    "end_date_optimization": "2025-09-26",
    "natr_min_min_optimization": 0.2,
    "natr_period_max_optimization": 80,
    "take_profit_pct_max_optimization": 5.0,
    "rng_pctl_min_optimization": 5,
    "range_period_min_optimization": 5,
    "stop_loss_pct_min_optimization": 1.0,
    "lookback_period_max_optimization": 50,
    "stop_loss_pct_max_optimization": 2.2,
    "profile_name_optimization": "",
    "save_profile_optimization": false,
    "vol_pctl_min_optimization": 2,
    "start_date_optimization": "2025-09-01",
    "position_size_optimization": 100.0,
    "natr_period_min_optimization": 1,
    "min_growth_pct_max_optimization": 2.0,
    "select_all_data_optimization": false,
    "rng_pctl_max_optimization": 30,
    "name_optimization": "0Orders",
    "commission_optimization": 0.1,
    "lookback_period_min_optimization": 1,
    "bracket_offset_pct_min_optimization": 0.2,
    "entry_logic_mode_optimization": "Вилка отложенных ордеров",
    "vol_pctl_max_optimization": 30
  },
  "settings": {
    "position_size": 100.0,
    "commission": 0.1,
    "aggressive_mode": false,
    "start_date": "2025-09-01",
    "end_date": "2025-09-26"
  },
  "data_files": [
    "50HEMIUSDT-klines-1s-2025-09-01_to_2025-09-30.parquet"
  ],
  "best_params": {
    "classifier_type": "RandomForest",
    "rf_n_estimators": 149,
    "rf_max_depth": 11,
    "vol_period": 28,
    "vol_pctl": 27,
    "range_period": 22,
    "rng_pctl": 15,
    "natr_period": 57,
    "natr_min": 0.37241190997151763,
    "lookback_period": 35,
    "min_growth_pct": 1.7572154488041232,
    "stop_loss_pct": 1.8910571633312911,
    "take_profit_pct": 2.7808139086878123,
    "entry_logic_mode": "Вилка отложенных ордеров",
    "bracket_offset_pct": 0.31077590506325675,
    "bracket_timeout_candles": 15
  },
  "optimization_type": "optuna_iterative",
  "top_10_results": [
    {
      "classifier_type": "RandomForest",
      "rf_n_estimators": 149,
      "rf_max_depth": 11,
      "vol_period": 28,
      "vol_pctl": 27,
      "range_period": 22,
      "rng_pctl": 15,
      "natr_period": 57,
      "natr_min": 0.37241190997151763,
      "lookback_period": 35,
      "min_growth_pct": 1.7572154488041232,
      "stop_loss_pct": 1.8910571633312911,
      "take_profit_pct": 2.7808139086878123,
      "entry_logic_mode": "Вилка отложенных ордеров",
      "bracket_offset_pct": 0.31077590506325675,
      "bracket_timeout_candles": 15,
      "trial_number": 24,
      "value": 1.1084360663704862,
      "total_signals": 355,
      "total_trades": 27,
      "winning_trades": 15,
      "win_rate": 0.5555555555555556,
      "total_pnl": 13.62000000000021,
      "avg_pnl": 0.5044444444444522,
      "max_drawdown": 0.05779999999999959,
      "profit_factor": 1.5430622009569483,
      "final_balance": 113.62000000000025,
      "used_params": [
        "bracket_timeout_candles",
        "commission",
        "natr_period",
        "lookback_period",
        "min_growth_pct",
        "vol_period",
        "bracket_offset_pct",
        "natr_min",
        "stop_loss_pct",
        "vol_pctl",
        "range_period",
        "position_size",
        "classifier_type",
        "rng_pctl",
        "take_profit_pct"
      ],
      "classifier_details": "{}"
    },
    {
      "classifier_type": "RandomForest",
      "rf_n_estimators": 132,
      "rf_max_depth": 18,
      "vol_period": 27,
      "vol_pctl": 27,
      "range_period": 28,
      "rng_pctl": 18,
      "natr_period": 80,
      "natr_min": 0.29909373001855066,
      "lookback_period": 42,
      "min_growth_pct": 1.3893699490155789,
      "stop_loss_pct": 1.898255357059926,
      "take_profit_pct": 3.7977647272432904,
      "entry_logic_mode": "Вилка отложенных ордеров",
      "bracket_offset_pct": 0.2579148393278856,
      "bracket_timeout_candles": 20,
      "trial_number": 19,
      "value": 1.0384870313036045,
      "total_signals": 740,
      "total_trades": 35,
      "winning_trades": 16,
      "win_rate": 0.45714285714285713,
      "total_pnl": 17.700000000000244,
      "avg_pnl": 0.5057142857142927,
      "max_drawdown": 0.10194174757281509,
      "profit_factor": 1.4436090225563993,
      "final_balance": 117.70000000000022,
      "used_params": [
        "bracket_timeout_candles",
        "commission",
        "natr_period",
        "lookback_period",
        "min_growth_pct",
        "vol_period",
        "bracket_offset_pct",
        "natr_min",
        "stop_loss_pct",
        "vol_pctl",
        "range_period",
        "position_size",
        "classifier_type",
        "rng_pctl",
        "take_profit_pct"
      ],
      "classifier_details": "{}"
    },
    {
      "classifier_type": "RandomForest",
      "rf_n_estimators": 131,
      "rf_max_depth": 14,
      "vol_period": 30,
      "vol_pctl": 30,
      "range_period": 24,
      "rng_pctl": 18,
      "natr_period": 44,
      "natr_min": 0.41880202695732294,
      "lookback_period": 35,
      "min_growth_pct": 1.345578663402409,
      "stop_loss_pct": 2.059693346410687,
      "take_profit_pct": 3.081471139090493,
      "entry_logic_mode": "Вилка отложенных ордеров",
      "bracket_offset_pct": 0.39920531572085394,
      "bracket_timeout_candles": 18,
      "trial_number": 37,
      "value": 0.6929238989987486,
      "total_signals": 434,
      "total_trades": 34,
      "winning_trades": 17,
      "win_rate": 0.5,
      "total_pnl": 10.539999999999948,
      "avg_pnl": 0.30999999999999844,
      "max_drawdown": 0.08786936236391879,
      "profit_factor": 1.2743362831858398,
      "final_balance": 110.53999999999996,
      "used_params": [
        "bracket_timeout_candles",
        "commission",
        "natr_period",
        "lookback_period",
        "min_growth_pct",
        "vol_period",
        "bracket_offset_pct",
        "natr_min",
        "stop_loss_pct",
        "vol_pctl",
        "range_period",
        "position_size",
        "classifier_type",
        "rng_pctl",
        "take_profit_pct"
      ],
      "classifier_details": "{}"
    },
    {
      "classifier_type": "RandomForest",
      "rf_n_estimators": 157,
      "rf_max_depth": 27,
      "vol_period": 30,
      "vol_pctl": 30,
      "range_period": 24,
      "rng_pctl": 18,
      "natr_period": 79,
      "natr_min": 0.4120756336942332,
      "lookback_period": 37,
      "min_growth_pct": 1.3360032405508833,
      "stop_loss_pct": 2.123030811137401,
      "take_profit_pct": 3.200302243849227,
      "entry_logic_mode": "Вилка отложенных ордеров",
      "bracket_offset_pct": 0.4000674301505499,
      "bracket_timeout_candles": 16,
      "trial_number": 43,
      "value": 0.46321961729701416,
      "total_signals": 374,
      "total_trades": 27,
      "winning_trades": 13,
      "win_rate": 0.48148148148148145,
      "total_pnl": 6.519999999999893,
      "avg_pnl": 0.24148148148147752,
      "max_drawdown": 0.09820521503555765,
      "profit_factor": 1.200738916256154,
      "final_balance": 106.5199999999999,
      "used_params": [
        "bracket_timeout_candles",
        "commission",
        "natr_period",
        "lookback_period",
        "min_growth_pct",
        "vol_period",
        "bracket_offset_pct",
        "natr_min",
        "stop_loss_pct",
        "vol_pctl",
        "range_period",
        "position_size",
        "classifier_type",
        "rng_pctl",
        "take_profit_pct"
      ],
      "classifier_details": "{}"
    },
    {
      "classifier_type": "RandomForest",
      "rf_n_estimators": 54,
      "rf_max_depth": 30,
      "vol_period": 30,
      "vol_pctl": 27,
      "range_period": 23,
      "rng_pctl": 18,
      "natr_period": 48,
      "natr_min": 0.42456868327586317,
      "lookback_period": 39,
      "min_growth_pct": 1.2297122569061112,
      "stop_loss_pct": 2.1943447813121124,
      "take_profit_pct": 3.2341493867178874,
      "entry_logic_mode": "Вилка отложенных ордеров",
      "bracket_offset_pct": 0.38378713192867786,
      "bracket_timeout_candles": 22,
      "trial_number": 47,
      "value": 0.37047875580825823,
      "total_signals": 431,
      "total_trades": 36,
      "winning_trades": 17,
      "win_rate": 0.4722222222222222,
      "total_pnl": 6.099999999999955,
      "avg_pnl": 0.1694444444444432,
      "max_drawdown": 0.11732465530530126,
      "profit_factor": 1.1343316450121106,
      "final_balance": 106.1,
      "used_params": [
        "bracket_timeout_candles",
        "commission",
        "natr_period",
        "lookback_period",
        "min_growth_pct",
        "vol_period",
        "bracket_offset_pct",
        "natr_min",
        "stop_loss_pct",
        "vol_pctl",
        "range_period",
        "position_size",
        "classifier_type",
        "rng_pctl",
        "take_profit_pct"
      ],
      "classifier_details": "{}"
    },
    {
      "classifier_type": "RandomForest",
      "rf_n_estimators": 52,
      "rf_max_depth": 27,
      "vol_period": 29,
      "vol_pctl": 27,
      "range_period": 30,
      "rng_pctl": 10,
      "natr_period": 51,
      "natr_min": 0.404507902705886,
      "lookback_period": 39,
      "min_growth_pct": 1.9058277438775153,
      "stop_loss_pct": 2.183226350136114,
      "take_profit_pct": 3.1442411052335086,
      "entry_logic_mode": "Вилка отложенных ордеров",
      "bracket_offset_pct": 0.31847281537202377,
      "bracket_timeout_candles": 20,
      "trial_number": 49,
      "value": 0.31997895733072623,
      "total_signals": 190,
      "total_trades": 25,
      "winning_trades": 12,
      "win_rate": 0.48,
      "total_pnl": 4.340000000000076,
      "avg_pnl": 0.17360000000000306,
      "max_drawdown": 0.09466984884645994,
      "profit_factor": 1.1402714932126718,
      "final_balance": 104.34000000000005,
      "used_params": [
        "bracket_timeout_candles",
        "commission",
        "natr_period",
        "lookback_period",
        "min_growth_pct",
        "vol_period",
        "bracket_offset_pct",
        "natr_min",
        "stop_loss_pct",
        "vol_pctl",
        "range_period",
        "position_size",
        "classifier_type",
        "rng_pctl",
        "take_profit_pct"
      ],
      "classifier_details": "{}"
    },
    {
      "classifier_type": "RandomForest",
      "rf_n_estimators": 63,
      "rf_max_depth": 25,
      "vol_period": 29,
      "vol_pctl": 30,
      "range_period": 24,
      "rng_pctl": 18,
      "natr_period": 43,
      "natr_min": 0.5461986438457149,
      "lookback_period": 37,
      "min_growth_pct": 1.2961070984428973,
      "stop_loss_pct": 2.162588389941375,
      "take_profit_pct": 2.837336003152725,
      "entry_logic_mode": "Вилка отложенных ордеров",
      "bracket_offset_pct": 0.3962101167029911,
      "bracket_timeout_candles": 20,
      "trial_number": 31,
      "value": 0.2799999999999918,
      "total_signals": 215,
      "total_trades": 26,
      "winning_trades": 13,
      "win_rate": 0.5,
      "total_pnl": 3.6399999999998958,
      "avg_pnl": 0.139999999999996,
      "max_drawdown": 0.12020373514431301,
      "profit_factor": 1.1186440677966067,
      "final_balance": 103.63999999999989,
      "used_params": [
        "bracket_timeout_candles",
        "commission",
        "natr_period",
        "lookback_period",
        "min_growth_pct",
        "vol_period",
        "bracket_offset_pct",
        "natr_min",
        "stop_loss_pct",
        "vol_pctl",
        "range_period",
        "position_size",
        "classifier_type",
        "rng_pctl",
        "take_profit_pct"
      ],
      "classifier_details": "{}"
    },
    {
      "classifier_type": "RandomForest",
      "rf_n_estimators": 191,
      "rf_max_depth": 26,
      "vol_period": 30,
      "vol_pctl": 30,
      "range_period": 24,
      "rng_pctl": 18,
      "natr_period": 79,
      "natr_min": 0.41476929245159466,
      "lookback_period": 36,
      "min_growth_pct": 1.396871255520701,
      "stop_loss_pct": 2.1830313937517527,
      "take_profit_pct": 2.7357628529956433,
      "entry_logic_mode": "Вилка отложенных ордеров",
      "bracket_offset_pct": 0.4069474132298021,
      "bracket_timeout_candles": 17,
      "trial_number": 41,
      "value": 0.18106550773431043,
      "total_signals": 350,
      "total_trades": 32,
      "winning_trades": 16,
      "win_rate": 0.5,
      "total_pnl": 2.5600000000000183,
      "avg_pnl": 0.08000000000000057,
      "max_drawdown": 0.10271216097987779,
      "profit_factor": 1.067226890756303,
      "final_balance": 102.56000000000003,
      "used_params": [
        "bracket_timeout_candles",
        "commission",
        "natr_period",
        "lookback_period",
        "min_growth_pct",
        "vol_period",
        "bracket_offset_pct",
        "natr_min",
        "stop_loss_pct",
        "vol_pctl",
        "range_period",
        "position_size",
        "classifier_type",
        "rng_pctl",
        "take_profit_pct"
      ],
      "classifier_details": "{}"
    },
    {
      "classifier_type": "RandomForest",
      "rf_n_estimators": 66,
      "rf_max_depth": 26,
      "vol_period": 30,
      "vol_pctl": 29,
      "range_period": 24,
      "rng_pctl": 16,
      "natr_period": 66,
      "natr_min": 0.41323777826894126,
      "lookback_period": 35,
      "min_growth_pct": 1.3721265938196778,
      "stop_loss_pct": 2.198003936304131,
      "take_profit_pct": 2.8484246642746336,
      "entry_logic_mode": "Вилка отложенных ордеров",
      "bracket_offset_pct": 0.4001788809052672,
      "bracket_timeout_candles": 18,
      "trial_number": 39,
      "value": 0.09451427273284985,
      "total_signals": 333,
      "total_trades": 31,
      "winning_trades": 15,
      "win_rate": 0.4838709677419355,
      "total_pnl": 1.3499999999999215,
      "avg_pnl": 0.04354838709677166,
      "max_drawdown": 0.10389036251105224,
      "profit_factor": 1.035156249999998,
      "final_balance": 101.34999999999992,
      "used_params": [
        "bracket_timeout_candles",
        "commission",
        "natr_period",
        "lookback_period",
        "min_growth_pct",
        "vol_period",
        "bracket_offset_pct",
        "natr_min",
        "stop_loss_pct",
        "vol_pctl",
        "range_period",
        "position_size",
        "classifier_type",
        "rng_pctl",
        "take_profit_pct"
      ],
      "classifier_details": "{}"
    },
    {
      "classifier_type": "RandomForest",
      "rf_n_estimators": 126,
      "rf_max_depth": 27,
      "vol_period": 27,
      "vol_pctl": 29,
      "range_period": 27,
      "rng_pctl": 10,
      "natr_period": 60,
      "natr_min": 0.3322447943599568,
      "lookback_period": 32,
      "min_growth_pct": 1.9129540076784926,
      "stop_loss_pct": 2.176363364340873,
      "take_profit_pct": 3.22961008842114,
      "entry_logic_mode": "Вилка отложенных ордеров",
      "bracket_offset_pct": 0.23938240105789665,
      "bracket_timeout_candles": 18,
      "trial_number": 3,
      "value": 0.04636572893193642,
      "total_signals": 239,
      "total_trades": 27,
      "winning_trades": 12,
      "win_rate": 0.4444444444444444,
      "total_pnl": 0.65999999999991,
      "avg_pnl": 0.02444444444444111,
      "max_drawdown": 0.1904000000000002,
      "profit_factor": 1.0184873949579807,
      "final_balance": 100.65999999999993,
      "used_params": [
        "bracket_timeout_candles",
        "commission",
        "natr_period",
        "lookback_period",
        "min_growth_pct",
        "vol_period",
        "bracket_offset_pct",
        "natr_min",
        "stop_loss_pct",
        "vol_pctl",
        "range_period",
        "position_size",
        "classifier_type",
        "rng_pctl",
        "take_profit_pct"
      ],
      "classifier_details": "{}"
    }
  ]
}