{
  "run_name": "run_20251018_153044_50HEMIUSDT_ITERATIVE_$3_OPTUNA",
  "timestamp": "2025-10-18T15:30:44.795556",
  "ranges": {
    "lookback_period_max_optimization": 50,
    "save_profile_optimization": false,
    "vol_pctl_max_optimization": 25,
    "vol_period_min_optimization": 1,
    "natr_min_min_optimization": 0.01,
    "vol_pctl_min_optimization": 1,
    "entry_logic_mode_optimization": "Вилка отложенных ордеров",
    "commission_optimization": 0.1,
    "end_date_optimization": "2025-09-26",
    "natr_period_min_optimization": 1,
    "hldir_offset_min_optimization": 0,
    "selected_files_optimization": [
      "50HEMIUSDT-klines-1s-2025-09-01_to_2025-09-30.parquet"
    ],
    "take_profit_pct_min_optimization": 0.5,
    "bracket_offset_pct_max_optimization": 1.0,
    "bracket_timeout_candles_max_optimization": 10,
    "vol_period_max_optimization": 30,
    "name_optimization": "123456789",
    "profile_name_optimization": "",
    "load_profile_optimization": false,
    "natr_period_max_optimization": 50,
    "bracket_timeout_candles_min_optimization": 1,
    "hldir_window_min_optimization": 5,
    "range_period_max_optimization": 30,
    "lookback_period_min_optimization": 1,
    "select_profile_optimization": "123456789",
    "rng_pctl_max_optimization": 1,
    "aggressive_mode_optimization": false,
    "hldir_window_max_optimization": 20,
    "take_profit_pct_max_optimization": 3.5,
    "min_growth_pct_min_optimization": 0.01,
    "stop_loss_pct_max_optimization": 2.1,
    "natr_min_max_optimization": 1.0,
    "hldir_offset_max_optimization": 10,
    "bracket_offset_pct_min_optimization": 0.2,
    "range_period_min_optimization": 1,
    "stop_loss_pct_min_optimization": 0.5,
    "select_all_data_optimization": false,
    "min_growth_pct_max_optimization": 2.0,
    "rng_pctl_min_optimization": 1,
    "start_date_optimization": "2025-09-01",
    "position_size_optimization": 100.0
  },
  "settings": {
    "position_size": 100.0,
    "commission": 0.1,
    "aggressive_mode": false,
    "start_date": "2025-09-01",
    "end_date": "2025-09-26"
  },
  "data_files": [
    "50HEMIUSDT-klines-1s-2025-09-01_to_2025-09-30.parquet"
  ],
  "best_params": {
    "classifier_type": "CatBoost",
    "prints_analysis_period": 9,
    "prints_threshold_ratio": 1.6454301694395643,
    "m_analysis_period": 3,
    "m_threshold_ratio": 2.4136979314579174,
    "hldir_window": 13,
    "hldir_offset": 6,
    "catboost_iterations": 212,
    "catboost_depth": 6,
    "catboost_learning_rate": 0.13295073691289172,
    "vol_period": 19,
    "vol_pctl": 6,
    "range_period": 17,
    "rng_pctl": 1,
    "natr_period": 27,
    "natr_min": 0.18090445399339783,
    "lookback_period": 26,
    "min_growth_pct": 1.999788326198341,
    "stop_loss_pct": 1.7496312103558493,
    "take_profit_pct": 3.1124676837339162,
    "entry_logic_mode": "Вилка отложенных ордеров",
    "bracket_offset_pct": 0.36461487348008925,
    "bracket_timeout_candles": 9
  },
  "optimization_type": "optuna_iterative",
  "top_10_results": [
    {
      "classifier_type": "CatBoost",
      "prints_analysis_period": 9,
      "prints_threshold_ratio": 1.6454301694395643,
      "m_analysis_period": 3,
      "m_threshold_ratio": 2.4136979314579174,
      "hldir_window": 13,
      "hldir_offset": 6,
      "vol_period": 19,
      "vol_pctl": 6,
      "range_period": 17,
      "rng_pctl": 1,
      "natr_period": 27,
      "natr_min": 0.18090445399339783,
      "lookback_period": 26,
      "min_growth_pct": 1.999788326198341,
      "stop_loss_pct": 1.7496312103558493,
      "take_profit_pct": 3.1124676837339162,
      "entry_logic_mode": "Вилка отложенных ордеров",
      "bracket_offset_pct": 0.36461487348008925,
      "bracket_timeout_candles": 9,
      "trial_number": 35,
      "value": 2.5863644514638704,
      "total_signals": 147,
      "total_trades": 87,
      "winning_trades": 47,
      "win_rate": 0.5402298850574713,
      "total_pnl": 58.769999999999825,
      "avg_pnl": 0.6755172413793084,
      "max_drawdown": 0.06929021941902837,
      "profit_factor": 1.7534615384615353,
      "final_balance": 158.76999999999987,
      "feature_importances": null,
      "ml_rejected_signals": [],
      "ml_model": null,
      "ml_scaler": null,
      "ml_features_df": null,
      "is_ml_simulation": false,
      "classifier_details": "{'iterations': 212, 'depth': 6, 'learning_rate': 0.13295073691289172}"
    },
    {
      "classifier_type": "CatBoost",
      "prints_analysis_period": 9,
      "prints_threshold_ratio": 1.9750817581711693,
      "m_analysis_period": 3,
      "m_threshold_ratio": 2.4587042748883365,
      "hldir_window": 13,
      "hldir_offset": 6,
      "vol_period": 10,
      "vol_pctl": 1,
      "range_period": 17,
      "rng_pctl": 1,
      "natr_period": 10,
      "natr_min": 0.18951922188390719,
      "lookback_period": 25,
      "min_growth_pct": 1.4078620791969658,
      "stop_loss_pct": 2.006801001030308,
      "take_profit_pct": 3.0564675456246153,
      "entry_logic_mode": "Вилка отложенных ордеров",
      "bracket_offset_pct": 0.4232587599083003,
      "bracket_timeout_candles": 9,
      "trial_number": 37,
      "value": 2.10032692582757,
      "total_signals": 268,
      "total_trades": 139,
      "winning_trades": 73,
      "win_rate": 0.5251798561151079,
      "total_pnl": 62.91999999999963,
      "avg_pnl": 0.45266187050359447,
      "max_drawdown": 0.10722950024260075,
      "profit_factor": 1.431372549019605,
      "final_balance": 162.9199999999992,
      "feature_importances": null,
      "ml_rejected_signals": [],
      "ml_model": null,
      "ml_scaler": null,
      "ml_features_df": null,
      "is_ml_simulation": false,
      "classifier_details": "{'iterations': 293, 'depth': 5, 'learning_rate': 0.01138262477870926}"
    },
    {
      "classifier_type": "CatBoost",
      "prints_analysis_period": 9,
      "prints_threshold_ratio": 1.636394495030132,
      "m_analysis_period": 3,
      "m_threshold_ratio": 2.440037895819109,
      "hldir_window": 13,
      "hldir_offset": 6,
      "vol_period": 19,
      "vol_pctl": 6,
      "range_period": 18,
      "rng_pctl": 1,
      "natr_period": 18,
      "natr_min": 0.19007015960057497,
      "lookback_period": 25,
      "min_growth_pct": 1.9737580435728264,
      "stop_loss_pct": 1.5630002226242137,
      "take_profit_pct": 3.116710031220889,
      "entry_logic_mode": "Вилка отложенных ордеров",
      "bracket_offset_pct": 0.3624399610860568,
      "bracket_timeout_candles": 9,
      "trial_number": 36,
      "value": 2.0418053962221716,
      "total_signals": 139,
      "total_trades": 84,
      "winning_trades": 41,
      "win_rate": 0.4880952380952381,
      "total_pnl": 44.0399999999998,
      "avg_pnl": 0.5242857142857119,
      "max_drawdown": 0.08599931200550365,
      "profit_factor": 1.581923890063422,
      "final_balance": 144.0399999999999,
      "feature_importances": null,
      "ml_rejected_signals": [],
      "ml_model": null,
      "ml_scaler": null,
      "ml_features_df": null,
      "is_ml_simulation": false,
      "classifier_details": "{'iterations': 203, 'depth': 6, 'learning_rate': 0.1344367229320226}"
    },
    {
      "classifier_type": "CatBoost",
      "prints_analysis_period": 8,
      "prints_threshold_ratio": 2.5591232724846056,
      "m_analysis_period": 3,
      "m_threshold_ratio": 2.8241823331072364,
      "hldir_window": 13,
      "hldir_offset": 6,
      "vol_period": 18,
      "vol_pctl": 6,
      "range_period": 17,
      "rng_pctl": 1,
      "natr_period": 17,
      "natr_min": 0.19706267976689162,
      "lookback_period": 25,
      "min_growth_pct": 1.4880956747082177,
      "stop_loss_pct": 2.0264073718702464,
      "take_profit_pct": 2.660039788118768,
      "entry_logic_mode": "Вилка отложенных ордеров",
      "bracket_offset_pct": 0.4207369667735464,
      "bracket_timeout_candles": 9,
      "trial_number": 43,
      "value": 1.8494909763478848,
      "total_signals": 266,
      "total_trades": 141,
      "winning_trades": 78,
      "win_rate": 0.5531914893617021,
      "total_pnl": 51.38999999999979,
      "avg_pnl": 0.36446808510638146,
      "max_drawdown": 0.13168525776303902,
      "profit_factor": 1.3657911595131313,
      "final_balance": 151.39000000000001,
      "feature_importances": null,
      "ml_rejected_signals": [],
      "ml_model": null,
      "ml_scaler": null,
      "ml_features_df": null,
      "is_ml_simulation": false,
      "classifier_details": "{'iterations': 50, 'depth': 4, 'learning_rate': 0.13312124213256527}"
    },
    {
      "classifier_type": "CatBoost",
      "prints_analysis_period": 9,
      "prints_threshold_ratio": 1.6713158570801974,
      "m_analysis_period": 3,
      "m_threshold_ratio": 2.819546146840228,
      "hldir_window": 13,
      "hldir_offset": 6,
      "vol_period": 18,
      "vol_pctl": 6,
      "range_period": 17,
      "rng_pctl": 1,
      "natr_period": 18,
      "natr_min": 0.03911004888121597,
      "lookback_period": 26,
      "min_growth_pct": 1.4917577609240757,
      "stop_loss_pct": 2.0067412133418596,
      "take_profit_pct": 3.064947752196227,
      "entry_logic_mode": "Вилка отложенных ордеров",
      "bracket_offset_pct": 0.415734922002135,
      "bracket_timeout_candles": 9,
      "trial_number": 39,
      "value": 1.7372482997414886,
      "total_signals": 305,
      "total_trades": 152,
      "winning_trades": 77,
      "win_rate": 0.506578947368421,
      "total_pnl": 54.469999999999615,
      "avg_pnl": 0.3583552631578922,
      "max_drawdown": 0.11969052224371404,
      "profit_factor": 1.3286274509803897,
      "final_balance": 154.46999999999926,
      "feature_importances": null,
      "ml_rejected_signals": [],
      "ml_model": null,
      "ml_scaler": null,
      "ml_features_df": null,
      "is_ml_simulation": false,
      "classifier_details": "{'iterations': 284, 'depth': 4, 'learning_rate': 0.019604084576184316}"
    },
    {
      "classifier_type": "CatBoost",
      "prints_analysis_period": 7,
      "prints_threshold_ratio": 2.0929724851542795,
      "m_analysis_period": 4,
      "m_threshold_ratio": 2.4352554981576597,
      "hldir_window": 13,
      "hldir_offset": 7,
      "vol_period": 6,
      "vol_pctl": 9,
      "range_period": 17,
      "rng_pctl": 1,
      "natr_period": 21,
      "natr_min": 0.3348445730856802,
      "lookback_period": 30,
      "min_growth_pct": 1.1936661251680025,
      "stop_loss_pct": 1.6739489074684102,
      "take_profit_pct": 3.434110607598429,
      "entry_logic_mode": "Вилка отложенных ордеров",
      "bracket_offset_pct": 0.36284706663641864,
      "bracket_timeout_candles": 10,
      "trial_number": 21,
      "value": 1.5090918327314715,
      "total_signals": 235,
      "total_trades": 142,
      "winning_trades": 61,
      "win_rate": 0.4295774647887324,
      "total_pnl": 45.56000000000016,
      "avg_pnl": 0.32084507042253635,
      "max_drawdown": 0.12255710935464266,
      "profit_factor": 1.3007856341189687,
      "final_balance": 145.5600000000002,
      "feature_importances": null,
      "ml_rejected_signals": [],
      "ml_model": null,
      "ml_scaler": null,
      "ml_features_df": null,
      "is_ml_simulation": false,
      "classifier_details": "{'iterations': 82, 'depth': 6, 'learning_rate': 0.05962320143215783}"
    },
    {
      "classifier_type": "CatBoost",
      "prints_analysis_period": 8,
      "prints_threshold_ratio": 2.3961404027493427,
      "m_analysis_period": 5,
      "m_threshold_ratio": 2.479763575232774,
      "hldir_window": 14,
      "hldir_offset": 7,
      "vol_period": 13,
      "vol_pctl": 10,
      "range_period": 15,
      "rng_pctl": 1,
      "natr_period": 26,
      "natr_min": 0.1995083554258513,
      "lookback_period": 28,
      "min_growth_pct": 1.9548018285023336,
      "stop_loss_pct": 2.0207447792661317,
      "take_profit_pct": 2.986694027825264,
      "entry_logic_mode": "Вилка отложенных ордеров",
      "bracket_offset_pct": 0.3774372996597144,
      "bracket_timeout_candles": 10,
      "trial_number": 2,
      "value": 1.4408646172130988,
      "total_signals": 222,
      "total_trades": 124,
      "winning_trades": 63,
      "win_rate": 0.5080645161290323,
      "total_pnl": 40.350000000000165,
      "avg_pnl": 0.3254032258064529,
      "max_drawdown": 0.1119139640396571,
      "profit_factor": 1.2979618963225532,
      "final_balance": 140.35000000000016,
      "feature_importances": null,
      "ml_rejected_signals": [],
      "ml_model": null,
      "ml_scaler": null,
      "ml_features_df": null,
      "is_ml_simulation": false,
      "classifier_details": "{'iterations': 153, 'depth': 4, 'learning_rate': 0.011433117304567305}"
    },
    {
      "classifier_type": "CatBoost",
      "prints_analysis_period": 7,
      "prints_threshold_ratio": 1.6544164504106147,
      "m_analysis_period": 3,
      "m_threshold_ratio": 2.803928339959554,
      "hldir_window": 10,
      "hldir_offset": 7,
      "vol_period": 12,
      "vol_pctl": 5,
      "range_period": 16,
      "rng_pctl": 1,
      "natr_period": 11,
      "natr_min": 0.4528169106034704,
      "lookback_period": 14,
      "min_growth_pct": 1.2856459771453612,
      "stop_loss_pct": 1.96602253922481,
      "take_profit_pct": 2.493377749385334,
      "entry_logic_mode": "Вилка отложенных ордеров",
      "bracket_offset_pct": 0.4278628921929113,
      "bracket_timeout_candles": 8,
      "trial_number": 11,
      "value": 1.417882943870008,
      "total_signals": 50,
      "total_trades": 42,
      "winning_trades": 25,
      "win_rate": 0.5952380952380952,
      "total_pnl": 20.359999999999907,
      "avg_pnl": 0.48476190476190256,
      "max_drawdown": 0.11282140983033094,
      "profit_factor": 1.5519110870154473,
      "final_balance": 120.3599999999999,
      "feature_importances": null,
      "ml_rejected_signals": [],
      "ml_model": null,
      "ml_scaler": null,
      "ml_features_df": null,
      "is_ml_simulation": false,
      "classifier_details": "{'iterations': 297, 'depth': 4, 'learning_rate': 0.09169353193370564}"
    },
    {
      "classifier_type": "CatBoost",
      "prints_analysis_period": 9,
      "prints_threshold_ratio": 2.0483402593706783,
      "m_analysis_period": 2,
      "m_threshold_ratio": 2.906927099649831,
      "hldir_window": 13,
      "hldir_offset": 8,
      "vol_period": 5,
      "vol_pctl": 6,
      "range_period": 15,
      "rng_pctl": 1,
      "natr_period": 24,
      "natr_min": 0.2768968039426152,
      "lookback_period": 36,
      "min_growth_pct": 1.728896531035943,
      "stop_loss_pct": 1.8448925041947624,
      "take_profit_pct": 3.18517166223923,
      "entry_logic_mode": "Вилка отложенных ордеров",
      "bracket_offset_pct": 0.4863620264779495,
      "bracket_timeout_candles": 9,
      "trial_number": 28,
      "value": 1.392273051755996,
      "total_signals": 243,
      "total_trades": 117,
      "winning_trades": 55,
      "win_rate": 0.4700854700854701,
      "total_pnl": 37.97000000000042,
      "avg_pnl": 0.3245299145299181,
      "max_drawdown": 0.18456292106795202,
      "profit_factor": 1.3002055660974108,
      "final_balance": 137.97000000000054,
      "feature_importances": null,
      "ml_rejected_signals": [],
      "ml_model": null,
      "ml_scaler": null,
      "ml_features_df": null,
      "is_ml_simulation": false,
      "classifier_details": "{'iterations': 69, 'depth': 7, 'learning_rate': 0.11553936740697991}"
    },
    {
      "classifier_type": "CatBoost",
      "prints_analysis_period": 7,
      "prints_threshold_ratio": 1.9426614182895807,
      "m_analysis_period": 5,
      "m_threshold_ratio": 2.935376749931029,
      "hldir_window": 9,
      "hldir_offset": 5,
      "vol_period": 13,
      "vol_pctl": 2,
      "range_period": 19,
      "rng_pctl": 1,
      "natr_period": 17,
      "natr_min": 0.4638994633858042,
      "lookback_period": 14,
      "min_growth_pct": 1.1264271607811034,
      "stop_loss_pct": 1.8375332070248134,
      "take_profit_pct": 2.9903109180107608,
      "entry_logic_mode": "Вилка отложенных ордеров",
      "bracket_offset_pct": 0.5902925924083303,
      "bracket_timeout_candles": 8,
      "trial_number": 22,
      "value": 1.3667941431312742,
      "total_signals": 40,
      "total_trades": 27,
      "winning_trades": 15,
      "win_rate": 0.5555555555555556,
      "total_pnl": 17.370000000000122,
      "avg_pnl": 0.6433333333333379,
      "max_drawdown": 0.09923144274734871,
      "profit_factor": 1.7095588235294177,
      "final_balance": 117.37000000000015,
      "feature_importances": null,
      "ml_rejected_signals": [],
      "ml_model": null,
      "ml_scaler": null,
      "ml_features_df": null,
      "is_ml_simulation": false,
      "classifier_details": "{'iterations': 253, 'depth': 8, 'learning_rate': 0.15163562375627887}"
    }
  ]
}