{
  "run_name": "run_20251017_231744_50HEMIUSDT_ITERATIVE_$3_OPTUNA",
  "timestamp": "2025-10-17T23:17:44.854486",
  "ranges": {
    "select_all_data_optimization": false,
    "natr_min_max_optimization": 1.0,
    "name_optimization": "012345",
    "stop_loss_pct_min_optimization": 0.5,
    "rng_pctl_max_optimization": 1,
    "selected_files_optimization": [
      "50HEMIUSDT-klines-1s-2025-09-01_to_2025-09-30.parquet"
    ],
    "natr_min_min_optimization": 0.01,
    "vol_period_min_optimization": 1,
    "take_profit_pct_max_optimization": 3.5,
    "min_growth_pct_min_optimization": 0.01,
    "hldir_offset_min_optimization": 0,
    "vol_pctl_min_optimization": 1,
    "aggressive_mode_optimization": false,
    "bracket_offset_pct_min_optimization": 0.2,
    "save_profile_optimization": false,
    "start_date_optimization": "2025-09-01",
    "lookback_period_max_optimization": 50,
    "commission_optimization": 0.1,
    "bracket_timeout_candles_min_optimization": 1,
    "rng_pctl_min_optimization": 1,
    "bracket_offset_pct_max_optimization": 1.0,
    "lookback_period_min_optimization": 1,
    "natr_period_max_optimization": 50,
    "range_period_min_optimization": 1,
    "stop_loss_pct_max_optimization": 2.1,
    "vol_pctl_max_optimization": 25,
    "bracket_timeout_candles_max_optimization": 10,
    "profile_name_optimization": "123456789",
    "take_profit_pct_min_optimization": 0.5,
    "hldir_window_min_optimization": 5,
    "min_growth_pct_max_optimization": 2.0,
    "entry_logic_mode_optimization": "Вилка отложенных ордеров",
    "position_size_optimization": 100.0,
    "hldir_offset_max_optimization": 10,
    "load_profile_optimization": false,
    "select_profile_optimization": "0!!!!!!!!!!!!!",
    "range_period_max_optimization": 30,
    "end_date_optimization": "2025-09-26",
    "hldir_window_max_optimization": 20,
    "natr_period_min_optimization": 1,
    "vol_period_max_optimization": 30
  },
  "settings": {
    "position_size": 100.0,
    "commission": 0.1,
    "aggressive_mode": false,
    "start_date": "2025-09-01",
    "end_date": "2025-09-26"
  },
  "data_files": [
    "50HEMIUSDT-klines-1s-2025-09-01_to_2025-09-30.parquet"
  ],
  "best_params": {
    "classifier_type": "CatBoost",
    "prints_analysis_period": 3,
    "prints_threshold_ratio": 1.6537765569389402,
    "m_analysis_period": 8,
    "m_threshold_ratio": 1.8310264015949425,
    "hldir_window": 17,
    "hldir_offset": 0,
    "catboost_iterations": 68,
    "catboost_depth": 6,
    "catboost_learning_rate": 0.03973237724434364,
    "vol_period": 23,
    "vol_pctl": 24,
    "range_period": 6,
    "rng_pctl": 1,
    "natr_period": 10,
    "natr_min": 0.8605063814574146,
    "lookback_period": 24,
    "min_growth_pct": 0.38027170624247586,
    "stop_loss_pct": 1.7016008685777824,
    "take_profit_pct": 2.7661787279764987,
    "entry_logic_mode": "Вилка отложенных ордеров",
    "bracket_offset_pct": 0.2648078080124141,
    "bracket_timeout_candles": 3
  },
  "optimization_type": "optuna_iterative",
  "top_10_results": [
    {
      "classifier_type": "CatBoost",
      "prints_analysis_period": 3,
      "prints_threshold_ratio": 1.6537765569389402,
      "m_analysis_period": 8,
      "m_threshold_ratio": 1.8310264015949425,
      "hldir_window": 17,
      "hldir_offset": 0,
      "vol_period": 23,
      "vol_pctl": 24,
      "range_period": 6,
      "rng_pctl": 1,
      "natr_period": 10,
      "natr_min": 0.8605063814574146,
      "lookback_period": 24,
      "min_growth_pct": 0.38027170624247586,
      "stop_loss_pct": 1.7016008685777824,
      "take_profit_pct": 2.7661787279764987,
      "entry_logic_mode": "Вилка отложенных ордеров",
      "bracket_offset_pct": 0.2648078080124141,
      "bracket_timeout_candles": 3,
      "trial_number": 80,
      "value": 2.8510421846196636,
      "total_signals": 65,
      "total_trades": 35,
      "winning_trades": 23,
      "win_rate": 0.6571428571428571,
      "total_pnl": 36.30999999999999,
      "avg_pnl": 1.0374285714285711,
      "max_drawdown": 0.07055983659827297,
      "profit_factor": 2.5925438596491253,
      "final_balance": 136.30999999999997,
      "feature_importances": null,
      "ml_rejected_signals": [],
      "ml_model": null,
      "ml_scaler": null,
      "ml_features_df": null,
      "is_ml_simulation": false,
      "classifier_details": "{'iterations': 68, 'depth': 6, 'learning_rate': 0.03973237724434364}"
    },
    {
      "classifier_type": "CatBoost",
      "prints_analysis_period": 3,
      "prints_threshold_ratio": 1.7988288225221178,
      "m_analysis_period": 6,
      "m_threshold_ratio": 1.8223710752054179,
      "hldir_window": 17,
      "hldir_offset": 0,
      "vol_period": 26,
      "vol_pctl": 24,
      "range_period": 6,
      "rng_pctl": 1,
      "natr_period": 10,
      "natr_min": 0.8532508418002783,
      "lookback_period": 25,
      "min_growth_pct": 0.3501136503908909,
      "stop_loss_pct": 1.8830064973804321,
      "take_profit_pct": 2.7913827057260923,
      "entry_logic_mode": "Вилка отложенных ордеров",
      "bracket_offset_pct": 0.26992632929620103,
      "bracket_timeout_candles": 3,
      "trial_number": 82,
      "value": 2.8374455779765864,
      "total_signals": 64,
      "total_trades": 34,
      "winning_trades": 23,
      "win_rate": 0.6764705882352942,
      "total_pnl": 36.690000000000126,
      "avg_pnl": 1.0791176470588273,
      "max_drawdown": 0.04532869235028875,
      "profit_factor": 2.6035839160839243,
      "final_balance": 136.69000000000014,
      "feature_importances": null,
      "ml_rejected_signals": [],
      "ml_model": null,
      "ml_scaler": null,
      "ml_features_df": null,
      "is_ml_simulation": false,
      "classifier_details": "{'iterations': 67, 'depth': 6, 'learning_rate': 0.039401557955270894}"
    },
    {
      "classifier_type": "CatBoost",
      "prints_analysis_period": 4,
      "prints_threshold_ratio": 1.739937204659954,
      "m_analysis_period": 7,
      "m_threshold_ratio": 1.9807013242779485,
      "hldir_window": 18,
      "hldir_offset": 0,
      "vol_period": 24,
      "vol_pctl": 23,
      "range_period": 4,
      "rng_pctl": 1,
      "natr_period": 11,
      "natr_min": 0.8905317668515629,
      "lookback_period": 22,
      "min_growth_pct": 0.2915840456577959,
      "stop_loss_pct": 1.4866776617378827,
      "take_profit_pct": 2.809508151441067,
      "entry_logic_mode": "Вилка отложенных ордеров",
      "bracket_offset_pct": 0.31222983652247865,
      "bracket_timeout_candles": 2,
      "trial_number": 49,
      "value": 2.6552800916035397,
      "total_signals": 65,
      "total_trades": 34,
      "winning_trades": 21,
      "win_rate": 0.6176470588235294,
      "total_pnl": 32.840000000000046,
      "avg_pnl": 0.9658823529411779,
      "max_drawdown": 0.04818475574985724,
      "profit_factor": 2.4947655894401506,
      "final_balance": 132.8400000000001,
      "feature_importances": null,
      "ml_rejected_signals": [],
      "ml_model": null,
      "ml_scaler": null,
      "ml_features_df": null,
      "is_ml_simulation": false,
      "classifier_details": "{'iterations': 58, 'depth': 5, 'learning_rate': 0.02672152592977152}"
    },
    {
      "classifier_type": "CatBoost",
      "prints_analysis_period": 3,
      "prints_threshold_ratio": 1.7939232408427765,
      "m_analysis_period": 6,
      "m_threshold_ratio": 1.8199909537150312,
      "hldir_window": 17,
      "hldir_offset": 0,
      "vol_period": 24,
      "vol_pctl": 24,
      "range_period": 5,
      "rng_pctl": 1,
      "natr_period": 14,
      "natr_min": 0.8534506538275088,
      "lookback_period": 24,
      "min_growth_pct": 0.3881641974470008,
      "stop_loss_pct": 1.900408394793751,
      "take_profit_pct": 2.8045848944296754,
      "entry_logic_mode": "Вилка отложенных ордеров",
      "bracket_offset_pct": 0.2582785603183133,
      "bracket_timeout_candles": 3,
      "trial_number": 88,
      "value": 2.4552038295597773,
      "total_signals": 69,
      "total_trades": 32,
      "winning_trades": 21,
      "win_rate": 0.65625,
      "total_pnl": 31.500000000000075,
      "avg_pnl": 0.9843750000000023,
      "max_drawdown": 0.060042887776983384,
      "profit_factor": 2.363636363636368,
      "final_balance": 131.50000000000006,
      "feature_importances": null,
      "ml_rejected_signals": [],
      "ml_model": null,
      "ml_scaler": null,
      "ml_features_df": null,
      "is_ml_simulation": false,
      "classifier_details": "{'iterations': 69, 'depth': 6, 'learning_rate': 0.05444761050297409}"
    },
    {
      "classifier_type": "CatBoost",
      "prints_analysis_period": 3,
      "prints_threshold_ratio": 1.7907669455952107,
      "m_analysis_period": 6,
      "m_threshold_ratio": 2.0970829063827137,
      "hldir_window": 17,
      "hldir_offset": 0,
      "vol_period": 24,
      "vol_pctl": 24,
      "range_period": 5,
      "rng_pctl": 1,
      "natr_period": 10,
      "natr_min": 0.8448878217915492,
      "lookback_period": 23,
      "min_growth_pct": 0.3987941483109919,
      "stop_loss_pct": 1.4254155629238845,
      "take_profit_pct": 2.841675532453172,
      "entry_logic_mode": "Вилка отложенных ордеров",
      "bracket_offset_pct": 0.259909770078941,
      "bracket_timeout_candles": 3,
      "trial_number": 94,
      "value": 2.4296942929848186,
      "total_signals": 70,
      "total_trades": 38,
      "winning_trades": 22,
      "win_rate": 0.5789473684210527,
      "total_pnl": 31.999999999999996,
      "avg_pnl": 0.8421052631578947,
      "max_drawdown": 0.048648648648648464,
      "profit_factor": 2.226993865030676,
      "final_balance": 131.99999999999997,
      "feature_importances": null,
      "ml_rejected_signals": [],
      "ml_model": null,
      "ml_scaler": null,
      "ml_features_df": null,
      "is_ml_simulation": false,
      "classifier_details": "{'iterations': 65, 'depth': 4, 'learning_rate': 0.02770774905671982}"
    },
    {
      "classifier_type": "CatBoost",
      "prints_analysis_period": 3,
      "prints_threshold_ratio": 1.798795925920176,
      "m_analysis_period": 6,
      "m_threshold_ratio": 1.6009752599929459,
      "hldir_window": 18,
      "hldir_offset": 0,
      "vol_period": 25,
      "vol_pctl": 24,
      "range_period": 5,
      "rng_pctl": 1,
      "natr_period": 14,
      "natr_min": 0.8564660968452752,
      "lookback_period": 24,
      "min_growth_pct": 0.21354025522384767,
      "stop_loss_pct": 1.8983462121772052,
      "take_profit_pct": 2.789266122728369,
      "entry_logic_mode": "Вилка отложенных ордеров",
      "bracket_offset_pct": 0.2652775147395495,
      "bracket_timeout_candles": 3,
      "trial_number": 86,
      "value": 2.395719989990254,
      "total_signals": 69,
      "total_trades": 34,
      "winning_trades": 22,
      "win_rate": 0.6470588235294118,
      "total_pnl": 31.78000000000013,
      "avg_pnl": 0.9347058823529449,
      "max_drawdown": 0.06737438075017656,
      "profit_factor": 2.2611111111111195,
      "final_balance": 131.78000000000014,
      "feature_importances": null,
      "ml_rejected_signals": [],
      "ml_model": null,
      "ml_scaler": null,
      "ml_features_df": null,
      "is_ml_simulation": false,
      "classifier_details": "{'iterations': 72, 'depth': 6, 'learning_rate': 0.0421038462555432}"
    },
    {
      "classifier_type": "CatBoost",
      "prints_analysis_period": 3,
      "prints_threshold_ratio": 1.7987283998227135,
      "m_analysis_period": 6,
      "m_threshold_ratio": 1.8405299917865323,
      "hldir_window": 17,
      "hldir_offset": 0,
      "vol_period": 25,
      "vol_pctl": 24,
      "range_period": 6,
      "rng_pctl": 1,
      "natr_period": 10,
      "natr_min": 0.8622288422853684,
      "lookback_period": 24,
      "min_growth_pct": 0.18888630550842178,
      "stop_loss_pct": 1.3505233415252362,
      "take_profit_pct": 2.826203185661457,
      "entry_logic_mode": "Вилка отложенных ордеров",
      "bracket_offset_pct": 0.2681305560289245,
      "bracket_timeout_candles": 3,
      "trial_number": 81,
      "value": 2.3637996008048368,
      "total_signals": 60,
      "total_trades": 35,
      "winning_trades": 20,
      "win_rate": 0.5714285714285714,
      "total_pnl": 29.34999999999994,
      "avg_pnl": 0.8385714285714269,
      "max_drawdown": 0.044176325289758886,
      "profit_factor": 2.262365591397847,
      "final_balance": 129.3499999999999,
      "feature_importances": null,
      "ml_rejected_signals": [],
      "ml_model": null,
      "ml_scaler": null,
      "ml_features_df": null,
      "is_ml_simulation": false,
      "classifier_details": "{'iterations': 69, 'depth': 6, 'learning_rate': 0.040678935968501216}"
    },
    {
      "classifier_type": "CatBoost",
      "prints_analysis_period": 2,
      "prints_threshold_ratio": 1.8860107440581273,
      "m_analysis_period": 8,
      "m_threshold_ratio": 1.7005221334726093,
      "hldir_window": 17,
      "hldir_offset": 0,
      "vol_period": 23,
      "vol_pctl": 16,
      "range_period": 7,
      "rng_pctl": 1,
      "natr_period": 9,
      "natr_min": 0.8810431249926445,
      "lookback_period": 23,
      "min_growth_pct": 0.38900719403697936,
      "stop_loss_pct": 1.840534812243412,
      "take_profit_pct": 2.8954609162242484,
      "entry_logic_mode": "Вилка отложенных ордеров",
      "bracket_offset_pct": 0.2462780966865156,
      "bracket_timeout_candles": 2,
      "trial_number": 2,
      "value": 2.348604470288545,
      "total_signals": 43,
      "total_trades": 26,
      "winning_trades": 17,
      "win_rate": 0.6538461538461539,
      "total_pnl": 27.54000000000002,
      "avg_pnl": 1.05923076923077,
      "max_drawdown": 0.04978848031239811,
      "profit_factor": 2.5000000000000036,
      "final_balance": 127.54000000000002,
      "feature_importances": null,
      "ml_rejected_signals": [],
      "ml_model": null,
      "ml_scaler": null,
      "ml_features_df": null,
      "is_ml_simulation": false,
      "classifier_details": "{'iterations': 108, 'depth': 6, 'learning_rate': 0.01975573654923432}"
    },
    {
      "classifier_type": "CatBoost",
      "prints_analysis_period": 4,
      "prints_threshold_ratio": 1.6776725281345093,
      "m_analysis_period": 8,
      "m_threshold_ratio": 1.8160915857809032,
      "hldir_window": 17,
      "hldir_offset": 0,
      "vol_period": 23,
      "vol_pctl": 21,
      "range_period": 6,
      "rng_pctl": 1,
      "natr_period": 10,
      "natr_min": 0.8617528238781765,
      "lookback_period": 24,
      "min_growth_pct": 0.3337754611503999,
      "stop_loss_pct": 1.8972174889385296,
      "take_profit_pct": 2.778265285222001,
      "entry_logic_mode": "Вилка отложенных ордеров",
      "bracket_offset_pct": 0.2621028000142274,
      "bracket_timeout_candles": 3,
      "trial_number": 78,
      "value": 2.2487868544301226,
      "total_signals": 57,
      "total_trades": 31,
      "winning_trades": 20,
      "win_rate": 0.6451612903225806,
      "total_pnl": 28.500000000000096,
      "avg_pnl": 0.9193548387096805,
      "max_drawdown": 0.046735905044510216,
      "profit_factor": 2.2337662337662385,
      "final_balance": 128.50000000000014,
      "feature_importances": null,
      "ml_rejected_signals": [],
      "ml_model": null,
      "ml_scaler": null,
      "ml_features_df": null,
      "is_ml_simulation": false,
      "classifier_details": "{'iterations': 69, 'depth': 6, 'learning_rate': 0.03655934383598408}"
    },
    {
      "classifier_type": "CatBoost",
      "prints_analysis_period": 4,
      "prints_threshold_ratio": 1.8535668705713997,
      "m_analysis_period": 7,
      "m_threshold_ratio": 2.0320212792490837,
      "hldir_window": 18,
      "hldir_offset": 0,
      "vol_period": 24,
      "vol_pctl": 23,
      "range_period": 4,
      "rng_pctl": 1,
      "natr_period": 22,
      "natr_min": 0.8879571987047234,
      "lookback_period": 22,
      "min_growth_pct": 0.26287834793604903,
      "stop_loss_pct": 1.506433843092147,
      "take_profit_pct": 2.76966458202675,
      "entry_logic_mode": "Вилка отложенных ордеров",
      "bracket_offset_pct": 0.305701643509417,
      "bracket_timeout_candles": 2,
      "trial_number": 39,
      "value": 2.003485212718627,
      "total_signals": 59,
      "total_trades": 27,
      "winning_trades": 16,
      "win_rate": 0.5925925925925926,
      "total_pnl": 22.31000000000008,
      "avg_pnl": 0.8262962962962993,
      "max_drawdown": 0.0465137365128295,
      "profit_factor": 2.1860712387028265,
      "final_balance": 122.31000000000009,
      "feature_importances": null,
      "ml_rejected_signals": [],
      "ml_model": null,
      "ml_scaler": null,
      "ml_features_df": null,
      "is_ml_simulation": false,
      "classifier_details": "{'iterations': 53, 'depth': 5, 'learning_rate': 0.011879679811663574}"
    }
  ]
}